z80count/__init__.py
z80count/z80count.py
z80count/z80table.json
z80count-0.8.2.dist-info/METADATA
z80count-0.8.2.dist-info/WHEEL
z80count-0.8.2.dist-info/entry_points.txt
z80count-0.8.2.dist-info/top_level.txt
z80count-0.8.2.dist-info/RECORD
