Metadata-Version: 2.1
Name: z80count
Version: 0.8.2
Summary: A tool to annotate Z80 assembler with cycle counts.
Home-page: https://git.usebox.net/z80count/about/
Author: Juan J. Martinez
Author-email: jjm@usebox.net
License: MIT
Classifier: Environment :: Console
Classifier: Intended Audience :: Developers
Classifier: License :: OSI Approved :: MIT License
Classifier: Programming Language :: Python :: 3 :: Only
Classifier: Topic :: Software Development
Provides-Extra: dev
Requires-Dist: pytest ; extra == 'dev'
Requires-Dist: tox ; extra == 'dev'
